flask_rdf/common_decorators.py
flask_rdf/wsgi.py
flask_rdf/__init__.py
flask_rdf/flask.py
flask_rdf/format.py
flask_rdf/bottle.py
flask_rdf-0.2.1.dist-info/top_level.txt
flask_rdf-0.2.1.dist-info/RECORD
flask_rdf-0.2.1.dist-info/METADATA
flask_rdf-0.2.1.dist-info/metadata.json
flask_rdf-0.2.1.dist-info/WHEEL
flask_rdf-0.2.1.dist-info/DESCRIPTION.rst
