Metadata-Version: 1.1
Name: flask-rdf
Version: 0.2.1
Summary: Flask decorator to output RDF using content negotiation
Home-page: https://github.com/hufman/flask_rdf
Author: Walter Huf
Author-email: hufman@gmail.com
License: BSD
Platform: Any
Classifier: Development Status :: 4 - Beta
Classifier: Framework :: Flask
Classifier: Intended Audience :: Developers
Classifier: License :: OSI Approved :: BSD License
Classifier: Operating System :: OS Independent
Classifier: Programming Language :: Python :: 2.6
Classifier: Programming Language :: Python :: 2.7
Classifier: Programming Language :: Python :: 3
Classifier: Programming Language :: Python :: 3.3
Classifier: Programming Language :: Python :: 3.4
Classifier: Programming Language :: Python :: 3.5
Classifier: Topic :: Internet :: WWW/HTTP :: Dynamic Content :: CGI Tools/Libraries
Classifier: Topic :: Software Development :: Libraries :: Python Modules
